siphon.py
siphon_cli-1.3.2.dist-info/METADATA
siphon_cli-1.3.2.dist-info/WHEEL
siphon_cli-1.3.2.dist-info/entry_points.txt
siphon_cli-1.3.2.dist-info/top_level.txt
siphon_cli-1.3.2.dist-info/RECORD
