Metadata-Version: 2.1
Name: siphon-cli
Version: 1.3.2
Summary: A tool to efficiently extract and compress Git repository contents for LLMs.
Home-page: https://github.com/atxtechbro/siphon
Author: Morgan Joyce
Author-email: morganj2k@gmail.com
Classifier: Programming Language :: Python :: 3
Classifier: License :: OSI Approved :: MIT License
Classifier: Operating System :: OS Independent
Requires-Python: >=3.6
Requires-Dist: gitpython
Requires-Dist: colorama
